sgposit
