Metadata-Version: 1.0
Name: sgposit
Version: 0.0.1.dev9
Summary: Posit arithmetic library for python
Home-page: https://github.com/xman/sgpositpy
Author: SpeedGo Computing
Author-email: shinyee@speedgocomputing.com
License: MIT
Keywords: posit arithmetic
Platform: UNKNOWN
